ivfit/__init__.py
ivfit/interactive_guess.py
ivfit/models.py
ivfit/parameter.py
ivfit/util.py
ivfit-0.1.0.dist-info/LICENSE
ivfit-0.1.0.dist-info/WHEEL
ivfit-0.1.0.dist-info/METADATA
ivfit-0.1.0.dist-info/RECORD
